fp_types/__init__.py
fp_types/apitypes.py
fp_types/datatypes.py
fp_types/errors.py
fp_types/features.py
fp_types/report_types.py
fp_types/retypes.py
fp_types/strategytype.py
fp_types/task_types.py
fp_types-1.0.3.dist-info/METADATA
fp_types-1.0.3.dist-info/WHEEL
fp_types-1.0.3.dist-info/top_level.txt
fp_types-1.0.3.dist-info/RECORD
