Metadata-Version: 2.1
Name: fp-types
Version: 1.0.3
Summary: Common Module and utils for my fp packages
Home-page: https://github.com/todhm/mini_bloomberg
Author: Fidel Kang
Author-email: gmlaud14@gmail.com
License: BSD-3
Platform: UNKNOWN
Classifier: License :: OSI Approved :: MIT License
Classifier: Programming Language :: Python
Classifier: Programming Language :: Python :: 3
Classifier: Programming Language :: Python :: 3.6
Classifier: Programming Language :: Python :: 3.7
Classifier: Programming Language :: Python :: 3.8
Classifier: Programming Language :: Python :: Implementation :: CPython
Classifier: Programming Language :: Python :: Implementation :: PyPy
Requires-Python: >=3.6.0
